dissolve/__init__.py
dissolve/ast_utils.py
dissolve/cli.py
dissolve/decorators.py
dissolve/py.typed
dissolve/tests/__init__.py
dissolve/tests/test_replace_me_decorator.py
dissolve-0.3.0.dist-info/licenses/COPYING
dissolve-0.3.0.dist-info/METADATA
dissolve-0.3.0.dist-info/WHEEL
dissolve-0.3.0.dist-info/entry_points.txt
dissolve-0.3.0.dist-info/top_level.txt
dissolve-0.3.0.dist-info/RECORD
