Metadata-Version: 2.4
Name: dissolve
Version: 0.3.0
Summary: Automatically replace use of deprecated APIs
Author-email: Jelmer Vernooĳ <jelmer@jelmer.uk>
License: Apachev2 or later
Project-URL: Homepage, https://github.com/jelmer/dissolve/
Classifier: Development Status :: 4 - Beta
Classifier: License :: OSI Approved :: GNU General Public License v3 or later (GPLv3+)
Classifier: Programming Language :: Python :: 3.9
Classifier: Programming Language :: Python :: 3.10
Classifier: Programming Language :: Python :: 3.11
Classifier: Programming Language :: Python :: 3.12
Classifier: Programming Language :: Python :: 3.13
Classifier: Programming Language :: Python :: Implementation :: CPython
Classifier: Programming Language :: Python :: Implementation :: PyPy
Classifier: Operating System :: POSIX
Requires-Python: >=3.9
License-File: COPYING
Requires-Dist: packaging
Provides-Extra: testing
Requires-Dist: pytest; extra == "testing"
Requires-Dist: pytest-asyncio; extra == "testing"
Provides-Extra: dev
Requires-Dist: ruff==0.11.11; extra == "dev"
Requires-Dist: mypy==1.15.0; extra == "dev"
Provides-Extra: tool
Dynamic: license-file
